segmix/__init__.py
segmix/cli.py
segmix/main.py
segmix-0.0.1.dist-info/METADATA
segmix-0.0.1.dist-info/WHEEL
segmix-0.0.1.dist-info/entry_points.txt
segmix-0.0.1.dist-info/top_level.txt
segmix-0.0.1.dist-info/RECORD
