Metadata-Version: 2.1
Name: segmix
Version: 0.0.1
Summary: Package for Mixing Stable Diffusiion XL Models by Segmind
Home-page: https://github.com/segmind/segmix
Author: Yatharth Gupta
Author-email: yatharthg@segmind.com
License: MIT
Platform: UNKNOWN
Requires-Dist: diffusers
Requires-Dist: safetensors
Requires-Dist: torch (>=2.0.0)
Requires-Dist: transformers
